<annotation>
	<folder>data</folder>
	<filename>4606911785_1b81bb8dd8_c.jpg</filename>
	<path>/Users/kevincollins/datahub/footwear/data/4606911785_1b81bb8dd8_c.jpg</path>
	<source>
		<database>Unknown</database>
	</source>
	<size>
		<width>571</width>
		<height>799</height>
		<depth>3</depth>
	</size>
	<segmented>0</segmented>
	<object>
		<name>footwear</name>
		<pose>Unspecified</pose>
		<truncated>0</truncated>
		<difficult>0</difficult>
		<bndbox>
			<xmin>170</xmin>
			<ymin>694</ymin>
			<xmax>212</xmax>
			<ymax>763</ymax>
		</bndbox>
	</object>
	<object>
		<name>footwear</name>
		<pose>Unspecified</pose>
		<truncated>0</truncated>
		<difficult>0</difficult>
		<bndbox>
			<xmin>300</xmin>
			<ymin>691</ymin>
			<xmax>397</xmax>
			<ymax>761</ymax>
		</bndbox>
	</object>
</annotation>
